saltrewrite/__init__.py
saltrewrite/__main__.py
saltrewrite/__main__.py~
saltrewrite/fixes.py
saltrewrite/imports/__init__.py
saltrewrite/imports/fix_tornado_imports.py
saltrewrite/salt/__init__.py
saltrewrite/salt/fix_docstrings.py
saltrewrite/salt/fix_docstrings.py~
saltrewrite/salt/fix_dunder_utils.py
saltrewrite/salt/fix_dunder_utils.py~
saltrewrite/testsuite/__init__.py
saltrewrite/testsuite/fix_asserts.py
saltrewrite/testsuite/fix_destructive_test_decorator.py
saltrewrite/testsuite/fix_expensive_test_decorator.py
saltrewrite/testsuite/fix_requires_network_decorator.py
saltrewrite/testsuite/fix_requires_salt_modules_decorator.py
saltrewrite/testsuite/fix_requires_salt_states_decorator.py
saltrewrite/testsuite/fix_skip_if_binaries_missing_decorator.py
saltrewrite/testsuite/fix_skip_if_not_root_decorator.py
saltrewrite/testsuite/fix_slow_test_decorator.py
saltrewrite/utils.py
salt_rewrite-2.4.4.dist-info/entry_points.txt
salt_rewrite-2.4.4.dist-info/LICENSE
salt_rewrite-2.4.4.dist-info/WHEEL
salt_rewrite-2.4.4.dist-info/METADATA
salt_rewrite-2.4.4.dist-info/RECORD
