Metadata-Version: 2.1
Name: salt-rewrite
Version: 2.4.4
Summary: A set of Bowler code to rewrite parts of Salt
License: Apache-2.0
Author: Pedro Algarvio
Author-email: pedro@algarvio.me
Requires-Python: >=3.8,<4
Classifier: License :: OSI Approved :: Apache Software License
Classifier: Programming Language :: Python :: 3
Classifier: Programming Language :: Python :: 3.10
Classifier: Programming Language :: Python :: 3.8
Classifier: Programming Language :: Python :: 3.9
Requires-Dist: bowler (>=0.9.0)
Requires-Dist: fissix (>=21.6,<22.0)
